my_backend/__init__.py
my_backend/main.py
lenstr-0.5.dist-info/METADATA
lenstr-0.5.dist-info/WHEEL
lenstr-0.5.dist-info/entry_points.txt
lenstr-0.5.dist-info/top_level.txt
lenstr-0.5.dist-info/RECORD
