Metadata-Version: 2.1
Name: lenstr
Version: 0.5
Requires-Dist: fastapi
Requires-Dist: uvicorn
Requires-Dist: jinja2
